odoo/addons/hr_timesheet_sheet_policy_department_manager/README.rst
odoo/addons/hr_timesheet_sheet_policy_department_manager/__init__.py
odoo/addons/hr_timesheet_sheet_policy_department_manager/__manifest__.py
odoo/addons/hr_timesheet_sheet_policy_department_manager/i18n/es.po
odoo/addons/hr_timesheet_sheet_policy_department_manager/i18n/fr.po
odoo/addons/hr_timesheet_sheet_policy_department_manager/i18n/hr_timesheet_sheet_policy_department_manager.pot
odoo/addons/hr_timesheet_sheet_policy_department_manager/models/__init__.py
odoo/addons/hr_timesheet_sheet_policy_department_manager/models/hr_timesheet_sheet.py
odoo/addons/hr_timesheet_sheet_policy_department_manager/models/res_company.py
odoo/addons/hr_timesheet_sheet_policy_department_manager/readme/CONTRIBUTORS.rst
odoo/addons/hr_timesheet_sheet_policy_department_manager/readme/DESCRIPTION.rst
odoo/addons/hr_timesheet_sheet_policy_department_manager/static/description/icon.png
odoo/addons/hr_timesheet_sheet_policy_department_manager/static/description/index.html
odoo/addons/hr_timesheet_sheet_policy_department_manager/tests/__init__.py
odoo/addons/hr_timesheet_sheet_policy_department_manager/tests/test_hr_timesheet_sheet_policy_department_manager.py
odoo/addons/hr_timesheet_sheet_policy_department_manager/views/hr_timesheet_sheet.xml
odoo12_addon_hr_timesheet_sheet_policy_department_manager-12.0.1.1.1.dist-info/METADATA
odoo12_addon_hr_timesheet_sheet_policy_department_manager-12.0.1.1.1.dist-info/WHEEL
odoo12_addon_hr_timesheet_sheet_policy_department_manager-12.0.1.1.1.dist-info/top_level.txt
odoo12_addon_hr_timesheet_sheet_policy_department_manager-12.0.1.1.1.dist-info/RECORD
